CHANGES.rst
LICENSE
MANIFEST.in
README.rst
setup.py
swingtix/__init__.py
swingtix/bookkeeper/__init__.py
swingtix/bookkeeper/account_api.py
swingtix/bookkeeper/models.py
swingtix/bookkeeper/test_docdocstrings.py
swingtix/bookkeeper/test_model.py
swingtix/bookkeeper/views.py
swingtix/bookkeeper/migrations/0001_initial.py
swingtix/bookkeeper/migrations/__init__.py
swingtix_bookkeeper.egg-info/PKG-INFO
swingtix_bookkeeper.egg-info/SOURCES.txt
swingtix_bookkeeper.egg-info/dependency_links.txt
swingtix_bookkeeper.egg-info/not-zip-safe
swingtix_bookkeeper.egg-info/requires.txt
swingtix_bookkeeper.egg-info/top_level.txt