Metadata-Version: 1.1
Name: swingtix-bookkeeper
Version: 0.0.6
Summary: A double-entry bookkeeping module for django
Home-page: https://github.com/swingtix/bookkeeper
Author: Geoff Oakham
Author-email: geoff.oakham@swingtix.ca
License: GNU Affero General Public License, version 3, see LICENSE
Platform: UNKNOWN
Classifier: Development Status :: 3 - Alpha
Classifier: Environment :: Web Environment
Classifier: Intended Audience :: Developers
Classifier: Intended Audience :: Financial and Insurance Industry
Classifier: Framework :: Django
Classifier: License :: OSI Approved :: GNU Affero General Public License v3
Classifier: Operating System :: OS Independent
Classifier: Programming Language :: Python
Classifier: Programming Language :: Python :: 2.7
Classifier: Topic :: Office/Business :: Financial :: Accounting
Classifier: Topic :: Software Development :: Libraries :: Python Modules
